json_schema_converter/__init__.py
json_schema_converter/generate_schema.py
generate_json_schema-0.1.5.dist-info/METADATA
generate_json_schema-0.1.5.dist-info/WHEEL
generate_json_schema-0.1.5.dist-info/top_level.txt
generate_json_schema-0.1.5.dist-info/RECORD
